django_expvar_cmdline-0.1.0.dist-info/DESCRIPTION.rst
django_expvar_cmdline-0.1.0.dist-info/METADATA
django_expvar_cmdline-0.1.0.dist-info/RECORD
django_expvar_cmdline-0.1.0.dist-info/WHEEL
django_expvar_cmdline-0.1.0.dist-info/metadata.json
django_expvar_cmdline-0.1.0.dist-info/top_level.txt
expvarcmdline/__init__.py
expvarcmdline/models.py
expvarcmdline/vars.py
